wildberries_sdk/__init__.py
wildberries_sdk/analytics/__init__.py
wildberries_sdk/analytics/api_client.py
wildberries_sdk/analytics/api_response.py
wildberries_sdk/analytics/configuration.py
wildberries_sdk/analytics/exceptions.py
wildberries_sdk/analytics/py.typed
wildberries_sdk/analytics/rest.py
wildberries_sdk/analytics/api/__init__.py
wildberries_sdk/analytics/api/default_api.py
wildberries_sdk/analytics/models/__init__.py
wildberries_sdk/analytics/models/api_v2_nm_report_downloads_get400_response.py
wildberries_sdk/analytics/models/api_v2_nm_report_downloads_get403_response.py
wildberries_sdk/analytics/models/api_v2_nm_report_downloads_post429_response.py
wildberries_sdk/analytics/models/api_v2_nm_report_downloads_post_request.py
wildberries_sdk/analytics/models/api_v2_search_report_product_orders_post200_response.py
wildberries_sdk/analytics/models/api_v2_search_report_product_search_texts_post200_response.py
wildberries_sdk/analytics/models/api_v2_search_report_report_post200_response.py
wildberries_sdk/analytics/models/api_v2_search_report_table_details_post200_response.py
wildberries_sdk/analytics/models/api_v2_search_report_table_groups_post200_response.py
wildberries_sdk/analytics/models/api_v2_stocks_report_offices_post200_response.py
wildberries_sdk/analytics/models/api_v2_stocks_report_products_groups_post200_response.py
wildberries_sdk/analytics/models/api_v2_stocks_report_products_products_post200_response.py
wildberries_sdk/analytics/models/api_v2_stocks_report_products_sizes_post200_response.py
wildberries_sdk/analytics/models/common_info.py
wildberries_sdk/analytics/models/common_info_advertised_products.py
wildberries_sdk/analytics/models/common_info_supplier_rating.py
wildberries_sdk/analytics/models/common_product_filters.py
wildberries_sdk/analytics/models/common_report_filters.py
wildberries_sdk/analytics/models/common_response_properties.py
wildberries_sdk/analytics/models/common_shipping_office_filters.py
wildberries_sdk-0.1.35.dist-info/LICENSE
wildberries_sdk-0.1.35.dist-info/METADATA
wildberries_sdk-0.1.35.dist-info/WHEEL
wildberries_sdk-0.1.35.dist-info/top_level.txt
wildberries_sdk-0.1.35.dist-info/RECORD
