Metadata-Version: 2.2
Name: wildberries-sdk
Version: 0.1.35
Summary: Wildberries OpenAPI clients (generated).
Author-email: Evgenii Lazarev <elazarev@gmail.com>
License: MIT
Project-URL: Homepage, https://github.com/eslazarev/wildberries-sdk
Project-URL: Documentation, https://eslazarev.github.io/wildberries-sdk/
Project-URL: Source, https://github.com/eslazarev/wildberries-sdk
Project-URL: Issues, https://github.com/eslazarev/wildberries-sdk/issues
Project-URL: Changelog, https://github.com/eslazarev/wildberries-sdk/blob/main/CHANGELOG.md
Keywords: wildberries,wb,api,sdk,openapi,marketplace,ecommerce,wildberries-api,вайлдберриз
Requires-Python: >=3.8
License-File: LICENSE
Requires-Dist: pydantic>=2.0.0
Requires-Dist: urllib3>=2.6.3
Requires-Dist: python-dateutil>=2.8.2
Requires-Dist: typing-extensions>=4.0.0
